lionweb_python-0.1.16.dist-info/licenses/LICENSE.txt
lionwebpython/__init__.py
lionwebpython/lionweb_version.py
lionwebpython/api/__init__.py
lionwebpython/api/classifier_instance_resolver.py
lionwebpython/api/composite_classifier_instance_resolver.py
lionwebpython/api/local_classifier_instance_resolver.py
lionwebpython/api/unresolved_classifier_instance_exception.py
lionwebpython/language/__init__.py
lionwebpython/language/annotation.py
lionwebpython/language/classifier.py
lionwebpython/language/concept.py
lionwebpython/language/containment.py
lionwebpython/language/data_type.py
lionwebpython/language/debug_utils.py
lionwebpython/language/enumeration.py
lionwebpython/language/enumeration_literal.py
lionwebpython/language/feature.py
lionwebpython/language/field.py
lionwebpython/language/ikeyed.py
lionwebpython/language/inamed.py
lionwebpython/language/interface.py
lionwebpython/language/language.py
lionwebpython/language/language_entity.py
lionwebpython/language/link.py
lionwebpython/language/lioncore_builtins.py
lionwebpython/language/namespace_provider.py
lionwebpython/language/namespaced_entity.py
lionwebpython/language/primitive_type.py
lionwebpython/language/property.py
lionwebpython/language/reference.py
lionwebpython/language/structured_data_type.py
lionwebpython/model/__init__.py
lionwebpython/model/annotation_instance.py
lionwebpython/model/classifier_instance.py
lionwebpython/model/classifier_instance_utils.py
lionwebpython/model/has_feature_values.py
lionwebpython/model/has_settable_parent.py
lionwebpython/model/node.py
lionwebpython/model/reference_value.py
lionwebpython/model/structured_data_type_instance.py
lionwebpython/model/structured_data_type_instance_utils.py
lionwebpython/model/impl/__init__.py
lionwebpython/model/impl/abstract_classifier_instance.py
lionwebpython/model/impl/dynamic_annotation_instance.py
lionwebpython/model/impl/dynamic_classifier_instance.py
lionwebpython/model/impl/dynamic_node.py
lionwebpython/model/impl/dynamic_structured_datype_instance.py
lionweb_python-0.1.16.dist-info/METADATA
lionweb_python-0.1.16.dist-info/WHEEL
lionweb_python-0.1.16.dist-info/top_level.txt
lionweb_python-0.1.16.dist-info/RECORD
