Metadata-Version: 2.4
Name: lionweb-python
Version: 0.1.16
Summary: A Python package for working with LionWeb
Author-email: Federico Tomassetti <federico@strumenta.com>
License:                                  Apache License
Requires-Python: >=3.8
License-File: LICENSE.txt
Requires-Dist: requests
Dynamic: license-file
